{
  "formatVersion": "1.1",
  "component": {
    "url": "../../aamsdk/1.2.3/aamsdk-1.2.3.module",
    "group": "com.adadapted",
    "module": "aamsdk",
    "version": "1.2.3",
    "attributes": {
      "org.gradle.status": "release"
    }
  },
  "createdBy": {
    "gradle": {
      "version": "7.5"
    }
  },
  "variants": [
    {
      "name": "releaseApiElements-published",
      "attributes": {
        "org.gradle.category": "library",
        "org.gradle.usage": "java-api",
        "org.jetbrains.kotlin.platform.type": "androidJvm"
      },
      "dependencies": [
        {
          "group": "org.jetbrains.kotlin",
          "module": "kotlin-stdlib-jdk8",
          "version": {
            "requires": "1.8.10"
          }
        }
      ],
      "files": [
        {
          "name": "aamsdk-release.aar",
          "url": "aamsdk-android-1.2.3.aar",
          "size": 414236,
          "sha512": "c744c711cb3ab3146ffc2cd2108ba4a56d3a458c4774286a2cef582ee200236d0cf9e6d215ed2126e9d3f355875cc0c58a124037d71ed71ae1bc4344320d1950",
          "sha256": "2ce52d795d440f3c7d9dfbbd0e626e023827952dcae3fafeab3d7c9e8650127f",
          "sha1": "11327e159bd953e76bf0f87326ea48589023588d",
          "md5": "841ef7a19622109127689b0577fac556"
        }
      ]
    },
    {
      "name": "releaseRuntimeElements-published",
      "attributes": {
        "org.gradle.category": "library",
        "org.gradle.usage": "java-runtime",
        "org.jetbrains.kotlin.platform.type": "androidJvm"
      },
      "dependencies": [
        {
          "group": "org.jetbrains.kotlin",
          "module": "kotlin-stdlib-jdk8",
          "version": {
            "requires": "1.8.10"
          },
          "excludes": [
            {
              "group": "org.jetbrains.kotlin",
              "module": "kotlin-stdlib-common"
            },
            {
              "group": "org.jetbrains.kotlin",
              "module": "kotlin-test-common"
            },
            {
              "group": "org.jetbrains.kotlin",
              "module": "kotlin-test-annotations-common"
            }
          ]
        },
        {
          "group": "com.google.android.material",
          "module": "material",
          "version": {
            "requires": "1.9.0"
          },
          "excludes": [
            {
              "group": "org.jetbrains.kotlin",
              "module": "kotlin-stdlib-common"
            },
            {
              "group": "org.jetbrains.kotlin",
              "module": "kotlin-test-common"
            },
            {
              "group": "org.jetbrains.kotlin",
              "module": "kotlin-test-annotations-common"
            }
          ]
        },
        {
          "group": "io.ktor",
          "module": "ktor-client-android",
          "version": {
            "requires": "2.2.3"
          },
          "excludes": [
            {
              "group": "org.jetbrains.kotlin",
              "module": "kotlin-stdlib-common"
            },
            {
              "group": "org.jetbrains.kotlin",
              "module": "kotlin-test-common"
            },
            {
              "group": "org.jetbrains.kotlin",
              "module": "kotlin-test-annotations-common"
            }
          ]
        },
        {
          "group": "com.google.android.gms",
          "module": "play-services-ads-identifier",
          "version": {
            "requires": "18.0.1"
          },
          "excludes": [
            {
              "group": "org.jetbrains.kotlin",
              "module": "kotlin-stdlib-common"
            },
            {
              "group": "org.jetbrains.kotlin",
              "module": "kotlin-test-common"
            },
            {
              "group": "org.jetbrains.kotlin",
              "module": "kotlin-test-annotations-common"
            }
          ]
        },
        {
          "group": "io.ktor",
          "module": "ktor-client-core",
          "version": {
            "requires": "2.2.3"
          },
          "excludes": [
            {
              "group": "org.jetbrains.kotlin",
              "module": "kotlin-stdlib-common"
            },
            {
              "group": "org.jetbrains.kotlin",
              "module": "kotlin-test-common"
            },
            {
              "group": "org.jetbrains.kotlin",
              "module": "kotlin-test-annotations-common"
            }
          ]
        },
        {
          "group": "io.ktor",
          "module": "ktor-serialization-kotlinx-json",
          "version": {
            "requires": "2.2.3"
          },
          "excludes": [
            {
              "group": "org.jetbrains.kotlin",
              "module": "kotlin-stdlib-common"
            },
            {
              "group": "org.jetbrains.kotlin",
              "module": "kotlin-test-common"
            },
            {
              "group": "org.jetbrains.kotlin",
              "module": "kotlin-test-annotations-common"
            }
          ]
        },
        {
          "group": "io.ktor",
          "module": "ktor-client-content-negotiation",
          "version": {
            "requires": "2.2.3"
          },
          "excludes": [
            {
              "group": "org.jetbrains.kotlin",
              "module": "kotlin-stdlib-common"
            },
            {
              "group": "org.jetbrains.kotlin",
              "module": "kotlin-test-common"
            },
            {
              "group": "org.jetbrains.kotlin",
              "module": "kotlin-test-annotations-common"
            }
          ]
        },
        {
          "group": "org.jetbrains.kotlinx",
          "module": "kotlinx-datetime",
          "version": {
            "requires": "0.4.0"
          },
          "excludes": [
            {
              "group": "org.jetbrains.kotlin",
              "module": "kotlin-stdlib-common"
            },
            {
              "group": "org.jetbrains.kotlin",
              "module": "kotlin-test-common"
            },
            {
              "group": "org.jetbrains.kotlin",
              "module": "kotlin-test-annotations-common"
            }
          ]
        },
        {
          "group": "org.jetbrains.kotlin",
          "module": "kotlin-stdlib-jdk7",
          "version": {
            "requires": "1.8.10"
          },
          "excludes": [
            {
              "group": "org.jetbrains.kotlin",
              "module": "kotlin-stdlib-common"
            },
            {
              "group": "org.jetbrains.kotlin",
              "module": "kotlin-test-common"
            },
            {
              "group": "org.jetbrains.kotlin",
              "module": "kotlin-test-annotations-common"
            }
          ]
        },
        {
          "group": "org.jetbrains.kotlinx",
          "module": "kotlinx-coroutines-core",
          "version": {
            "requires": "1.6.1"
          },
          "excludes": [
            {
              "group": "org.jetbrains.kotlin",
              "module": "kotlin-stdlib-common"
            },
            {
              "group": "org.jetbrains.kotlin",
              "module": "kotlin-test-common"
            },
            {
              "group": "org.jetbrains.kotlin",
              "module": "kotlin-test-annotations-common"
            }
          ]
        },
        {
          "group": "io.github.aakira",
          "module": "napier",
          "version": {
            "requires": "2.6.1"
          },
          "excludes": [
            {
              "group": "org.jetbrains.kotlin",
              "module": "kotlin-stdlib-common"
            },
            {
              "group": "org.jetbrains.kotlin",
              "module": "kotlin-test-common"
            },
            {
              "group": "org.jetbrains.kotlin",
              "module": "kotlin-test-annotations-common"
            }
          ]
        }
      ],
      "files": [
        {
          "name": "aamsdk-release.aar",
          "url": "aamsdk-android-1.2.3.aar",
          "size": 414236,
          "sha512": "c744c711cb3ab3146ffc2cd2108ba4a56d3a458c4774286a2cef582ee200236d0cf9e6d215ed2126e9d3f355875cc0c58a124037d71ed71ae1bc4344320d1950",
          "sha256": "2ce52d795d440f3c7d9dfbbd0e626e023827952dcae3fafeab3d7c9e8650127f",
          "sha1": "11327e159bd953e76bf0f87326ea48589023588d",
          "md5": "841ef7a19622109127689b0577fac556"
        }
      ]
    }
  ]
}
